carto2gpd/__init__.py
carto2gpd/core.py
carto2gpd/tests/__init__.py
carto2gpd/tests/test_get.py
carto2gpd/tests/test_get_size.py
carto2gpd-1.0.12.dist-info/LICENSE
carto2gpd-1.0.12.dist-info/WHEEL
carto2gpd-1.0.12.dist-info/METADATA
carto2gpd-1.0.12.dist-info/RECORD
