Metadata-Version: 2.1
Name: carto2gpd
Version: 1.0.12
Summary: A Python utility to query a CARTO database and return a geopandas GeoDataFrame
License: MIT
Author: Nick Hand
Author-email: nick.hand@phila.gov
Requires-Python: >=3.8,<4.0.0
Classifier: License :: OSI Approved :: MIT License
Classifier: Programming Language :: Python :: 3
Classifier: Programming Language :: Python :: 3.10
Classifier: Programming Language :: Python :: 3.8
Classifier: Programming Language :: Python :: 3.9
Requires-Dist: geopandas (>=0.6)
Requires-Dist: requests (>=2,<3)
